codeview/__init__.py
codeview/__main__.py
codeview/cli.py
codeview/colors.py
codeview/formatters.py
codeview/scanner.py
codeview/utils.py
codeview-1.0.0.dist-info/licenses/LICENSE
codeview-1.0.0.dist-info/METADATA
codeview-1.0.0.dist-info/WHEEL
codeview-1.0.0.dist-info/entry_points.txt
codeview-1.0.0.dist-info/top_level.txt
codeview-1.0.0.dist-info/RECORD
