Metadata-Version: 2.4
Name: codeview
Version: 1.0.0
Summary: A powerful tool to visualize codebases for LLM interactions
Home-page: https://github.com/ZiadAmerr/codeview
Author: Ziad Amerr
Author-email: Ziad Amerr <Ziad.amerr@yahoo.com>
License: MIT
Project-URL: Homepage, https://github.com/ZiadAmerr/codeview
Project-URL: Repository, https://github.com/ZiadAmerr/codeview
Project-URL: Issues, https://github.com/ZiadAmerr/codeview/issues
Keywords: code,visualization,llm,ai,development,documentation
Classifier: Development Status :: 5 - Production/Stable
Classifier: Intended Audience :: Developers
Classifier: Topic :: Software Development :: Documentation
Classifier: License :: OSI Approved :: MIT License
Classifier: Programming Language :: Python :: 3
Requires-Python: >=3.7
License-File: LICENSE
Dynamic: author
Dynamic: home-page
Dynamic: license-file
Dynamic: requires-python
